.gitignore
MANIFEST.in
README.rst
setup.cfg
setup.py
docs/HISTORY.rst
docs/LICENSE.GPL
docs/LICENSE.txt
docs/MANUAL.txt
raptus/__init__.py
raptus.article.files.egg-info/PKG-INFO
raptus.article.files.egg-info/SOURCES.txt
raptus.article.files.egg-info/dependency_links.txt
raptus.article.files.egg-info/entry_points.txt
raptus.article.files.egg-info/namespace_packages.txt
raptus.article.files.egg-info/not-zip-safe
raptus.article.files.egg-info/requires.txt
raptus.article.files.egg-info/top_level.txt
raptus/article/__init__.py
raptus/article/files/__init__.py
raptus/article/files/configure.zcml
raptus/article/files/files.py
raptus/article/files/interfaces.py
raptus/article/files/browser/__init__.py
raptus/article/files/browser/attachments.gif
raptus/article/files/browser/attachments.pt
raptus/article/files/browser/attachments.py
raptus/article/files/browser/configure.zcml
raptus/article/files/locales/raptus.article.pot
raptus/article/files/locales/de/LC_MESSAGES/raptus.article.mo
raptus/article/files/locales/de/LC_MESSAGES/raptus.article.po
raptus/article/files/locales/fr/LC_MESSAGES/raptus.article.mo
raptus/article/files/locales/fr/LC_MESSAGES/raptus.article.po
raptus/article/files/locales/it/LC_MESSAGES/raptus.article.mo
raptus/article/files/locales/it/LC_MESSAGES/raptus.article.po
raptus/article/files/profiles/default/metadata.xml
raptus/article/files/profiles/default/types.xml
raptus/article/files/profiles/default/viewlets.xml
raptus/article/files/profiles/default/workflows.xml
raptus/article/files/profiles/default/types/Article.xml