Metadata-Version: 1.1
Name: raptus.article.files
Version: 2.0b8
Summary: Provides support for adding attachments to articles.
Home-page: https://github.com/Raptus/raptus.article.files
Author: Raptus AG
Author-email: dev@raptus.com
License: GPL
Platform: UNKNOWN
Classifier: Programming Language :: Python
Classifier: Topic :: Software Development :: Libraries :: Python Modules
